NetHytech_STT/__int__.py
NetHytech_STT/setup.py
nethytech_stt_ram-0.1.dist-info/METADATA
nethytech_stt_ram-0.1.dist-info/WHEEL
nethytech_stt_ram-0.1.dist-info/top_level.txt
nethytech_stt_ram-0.1.dist-info/RECORD
