Metadata-Version: 2.4
Name: NetHyTech_STT-Ram
Version: 0.1
Summary: this is speech to text package created by a Ramsharma
Author: Ramsharma
Author-email: rambhakthanuman823975@gmail.com
Dynamic: author
Dynamic: author-email
Dynamic: summary
